regopy/__init__.py
regopy/interpreter.py
regopy/librego_shared.so
regopy/node.py
regopy/output.py
regopy/rego_shared.py
regopy-1.2.0.dist-info/METADATA
regopy-1.2.0.dist-info/WHEEL
regopy-1.2.0.dist-info/top_level.txt
regopy-1.2.0.dist-info/RECORD
