Metadata-Version: 2.4
Name: regopy
Version: 1.2.0
Summary: Python interface for the OPA Rego Language and Runtime
Home-page: https://microsoft.github.io/rego-cpp/
Author: rego-cpp Team
Author-email: rego-cpp@microsoft.com
License: MIT
Project-URL: Documentation, https://microsoft.github.io/rego-cpp/
Project-URL: Bug Reports, https://github.com/microsoft/rego-cpp/issues
Project-URL: Source, https://github.com/microsoft/rego-cpp
Classifier: Programming Language :: Python :: 3
Requires-Python: >=3.6, <4
Provides-Extra: dev
Requires-Dist: flake8; extra == "dev"
Requires-Dist: flake8-bugbear; extra == "dev"
Requires-Dist: flake8-builtins; extra == "dev"
Requires-Dist: flake8-docstrings; extra == "dev"
Requires-Dist: flake8-import-order; extra == "dev"
Requires-Dist: flake8-quotes; extra == "dev"
Requires-Dist: pep8-naming; extra == "dev"
Requires-Dist: pytest; extra == "dev"
Requires-Dist: sphinx; extra == "dev"
Requires-Dist: sphinx-autodoc-typehints; extra == "dev"
Requires-Dist: sphinx-rtd-theme; extra == "dev"
Requires-Dist: enum-tools[sphinx]; extra == "dev"
Requires-Dist: twine; extra == "dev"
Requires-Dist: wheel; extra == "dev"
Dynamic: author
Dynamic: author-email
Dynamic: classifier
Dynamic: description
Dynamic: description-content-type
Dynamic: home-page
Dynamic: license
Dynamic: project-url
Dynamic: provides-extra
Dynamic: requires-python
Dynamic: summary
